py_smallgames/__init__.py
py_smallgames/boxman/boxman.py
py_smallgames/boxman/mapeditor/__init__.py
py_smallgames/conway/__init__.py
py_smallgames/conway/conway.py
py_smallgames/libs/__init__.py
py_smallgames/libs/gameobj/__init__.py
py_smallgames/libs/gameobj/movingsprite.py
py_smallgames/libs/utils/__init__.py
py_smallgames/libs/utils/image.py
py_smallgames/magictower/__init__.py
py_smallgames/magictower/editor/__init__.py
py_smallgames/magictower/game/__init__.py
py_smallgames/rougelike/AStarSearch.py
py_smallgames/rougelike/GameMap.py
py_smallgames/rougelike/GameRole.py
py_smallgames/rougelike/MazeGenerator.py
py_smallgames/rougelike/resource/image/enemy1.png
py_smallgames/rougelike/resource/image/hero.jpg
py_smallgames/rougelike/resource/image/weapon1.png
py_smallgames/rougelike/resource/sound/weapon1.wav
py_smallgames/rougelike/RogueLikeMaze.py
py_smallgames/rougelike/rougelike.py
py_smallgames/rougelike/targets.txt
py_smallgames/snakegame/__init__.py
py_smallgames/snakegame/assets/images/snake.png
py_smallgames/snakegame/assets/music/snake.wav
py_smallgames/snakegame/assets/snake.ico
py_smallgames/snakegame/snakegame.py
py_smallgames/spaceship/assets/images/enemy1.gif
py_smallgames/spaceship/assets/images/enemy2.gif
py_smallgames/spaceship/assets/images/enemy3.gif
py_smallgames/spaceship/assets/images/gameover.gif
py_smallgames/spaceship/assets/images/ship.gif
py_smallgames/spaceship/assets/sounds/boom.wav
py_smallgames/spaceship/assets/sounds/highscore.wav
py_smallgames/spaceship/assets/sounds/shot.wav
py_smallgames/spaceship/assets/sounds/technotris.mp3
py_smallgames/spaceship/gameobj/__init__.py
py_smallgames/spaceship/gameobj/enemy.py
py_smallgames/spaceship/gameobj/gameobj.py
py_smallgames/spaceship/gameobj/particle.py
py_smallgames/spaceship/gameobj/ship.py
py_smallgames/spaceship/gameobj/shot.py
py_smallgames/spaceship/gameobj/star.py
py_smallgames/spaceship/highscore.spacegame
py_smallgames/spaceship/spaceship.py
py_smallgames/towerdefense/main.py
py_smallgames-0.1.5.dist-info/METADATA
py_smallgames-0.1.5.dist-info/WHEEL
py_smallgames-0.1.5.dist-info/RECORD
