Metadata-Version: 2.1
Name: py-smallgames
Version: 0.1.5
Summary: 
Author: Young
Author-email: gooker_young@163.com
Requires-Python: >=3.8,<4.0
Classifier: Programming Language :: Python :: 3
Classifier: Programming Language :: Python :: 3.8
Classifier: Programming Language :: Python :: 3.9
Classifier: Programming Language :: Python :: 3.10
Classifier: Programming Language :: Python :: 3.11
Classifier: Programming Language :: Python :: 3.12
Requires-Dist: numpy (>=1.24,<1.25)
Requires-Dist: pygame (>=2.6.0,<3.0.0)
